setup.py
ssl_expiry/__init__.py
ssl_expiry/ssl_expiry.py
ssl_expiry.egg-info/PKG-INFO
ssl_expiry.egg-info/SOURCES.txt
ssl_expiry.egg-info/dependency_links.txt
ssl_expiry.egg-info/entry_points.txt
ssl_expiry.egg-info/requires.txt
ssl_expiry.egg-info/top_level.txt