Metadata-Version: 1.1
Name: ssl-expiry
Version: 0.1.0
Summary: Quickly check when your SSL certificate expires from the command line
Home-page: https://github.com/sesh/ssl_expiry
Author: Brenton Cleeland
Author-email: brenton@brntn.me
License: MIT License
Platform: UNKNOWN
Classifier: Programming Language :: Python :: 2.7
Classifier: Programming Language :: Python :: 3
Classifier: Programming Language :: Python :: 3.5
